odoo/addons/sale_purchase_force_vendor/README.rst
odoo/addons/sale_purchase_force_vendor/__init__.py
odoo/addons/sale_purchase_force_vendor/__manifest__.py
odoo/addons/sale_purchase_force_vendor/i18n/es.po
odoo/addons/sale_purchase_force_vendor/i18n/it.po
odoo/addons/sale_purchase_force_vendor/i18n/nl.po
odoo/addons/sale_purchase_force_vendor/i18n/pt_BR.po
odoo/addons/sale_purchase_force_vendor/i18n/sale_purchase_force_vendor.pot
odoo/addons/sale_purchase_force_vendor/models/__init__.py
odoo/addons/sale_purchase_force_vendor/models/res_company.py
odoo/addons/sale_purchase_force_vendor/models/res_config_settings.py
odoo/addons/sale_purchase_force_vendor/models/sale_order_line.py
odoo/addons/sale_purchase_force_vendor/models/stock_move.py
odoo/addons/sale_purchase_force_vendor/readme/CONFIGURE.md
odoo/addons/sale_purchase_force_vendor/readme/CONTRIBUTORS.md
odoo/addons/sale_purchase_force_vendor/readme/DESCRIPTION.md
odoo/addons/sale_purchase_force_vendor/readme/USAGE.md
odoo/addons/sale_purchase_force_vendor/static/description/icon.png
odoo/addons/sale_purchase_force_vendor/static/description/index.html
odoo/addons/sale_purchase_force_vendor/tests/__init__.py
odoo/addons/sale_purchase_force_vendor/tests/common.py
odoo/addons/sale_purchase_force_vendor/tests/test_sale_purchase_force_vendor.py
odoo/addons/sale_purchase_force_vendor/views/res_config_settings_view.xml
odoo/addons/sale_purchase_force_vendor/views/sale_order_view.xml
odoo_addon_sale_purchase_force_vendor-18.0.1.0.0.3.dist-info/METADATA
odoo_addon_sale_purchase_force_vendor-18.0.1.0.0.3.dist-info/WHEEL
odoo_addon_sale_purchase_force_vendor-18.0.1.0.0.3.dist-info/top_level.txt
odoo_addon_sale_purchase_force_vendor-18.0.1.0.0.3.dist-info/RECORD
